pymonik/__init__.py
pymonik/context.py
pymonik/core.py
pymonik/environment.py
pymonik/materialize.py
pymonik/results.py
pymonik/utils.py
pymonik/worker.py
pymonik-0.2.5.dist-info/METADATA
pymonik-0.2.5.dist-info/WHEEL
pymonik-0.2.5.dist-info/RECORD
