Metadata-Version: 2.4
Name: pymonik
Version: 0.2.5
Summary: Lightweight Distributed Computing Framework
Requires-Python: >=3.10
Requires-Dist: armonik>=3.25.0
Requires-Dist: cloudpickle>=3.1.1
Requires-Dist: grpcio
Requires-Dist: pyyaml>=6.0.2
